{
    "title": "我神真伟大",
    "background": "resources/dimond.webm",
    "slides": [
        {
            "id": "slide0",
            "title": "标题",
            "lyrics": "我神真伟大"
        },
        {
            "id": "slide1",
            "title": "主歌",
            "lyrics": "尊贵荣耀君王，在全地之上<br>愿万民都喜乐，全地都喜乐"
        },
        {
            "id": "slide2",
            "title": "主歌 2",
            "lyrics": "主你满有荣光，黑暗都躲藏<br>万民高声唱，齐来高声唱"
        },
        {
            "id": "slide3",
            "title": "副歌",
            "lyrics": "我神，真伟大<br>歌颂你圣名，真伟大<br>全地都看见，我神真伟大"
        },
        {
            "id": "slide4",
            "title": "主歌 3",
            "lyrics": "昔在永在君王，从今直到永远<br>你从曾改变，永存在天地间"
        },
        {
            "id": "slide5",
            "title": "主歌 4",
            "lyrics": "你是三一真神，父子与圣灵<br>真神的羔羊，全能神羔羊"
        },
        {
            "id": "slide6",
            "title": "副歌",
            "lyrics": "我神，真伟大<br>歌颂你圣名，真伟大<br>全地都看见，我神真伟大"
        },
        {
            "id": "slide7",
            "title": "主歌 3",
            "lyrics": "昔在永在君王，从今直到永远<br>你从不曾改变，永存在天地间"
        },
        {
            "id": "slide8",
            "title": "桥",
            "lyrics": "你至圣尊名，配受大赞美<br>全心歌颂，我神真伟大"
        },
        {
            "id": "slide9",
            "title": "桥 2",
            "lyrics": "我神，真伟大<br>我神，真伟大"
        },
        {
            "id": "slide6",
            "title": "副歌",
            "lyrics": "我神，真伟大<br>歌颂你圣名，真伟大<br>全地都看见，我神真伟大"
        }
    ]
}